miley/__init__.py
miley/client.py
miley/container_handler.py
miley/dir_walker.py
miley/hasher.py
miley/main.py
miley-1.0.2.dist-info/LICENSE
miley-1.0.2.dist-info/METADATA
miley-1.0.2.dist-info/WHEEL
miley-1.0.2.dist-info/entry_points.txt
miley-1.0.2.dist-info/RECORD
