Metadata-Version: 2.1
Name: miley
Version: 1.0.2
Summary: TBD
Author: bluesentinelsec
Author-email: bluesentinel@protonmail.com
Requires-Python: >=3.9,<4.0
Classifier: Programming Language :: Python :: 3
Classifier: Programming Language :: Python :: 3.9
Classifier: Programming Language :: Python :: 3.10
Classifier: Programming Language :: Python :: 3.11
Requires-Dist: docker (>=6.1.3,<7.0.0)
Requires-Dist: requests (>=2.31.0,<3.0.0)
